{
	"cases_time_series": [
		{
			"dailyadmitted": 6,
			"dailytransferred": 0,
			"dailydischarged": 6,
			"date": "01 May",
			"totaladmitted": 6,
			"totaltransferred": 0,
			"totaldischarged": 6
		  },
		  {
			"dailyadmitted": 3,
			"dailytransferred": 0,
			"dailydischarged": 6,
			"date": "02 May",
			"totaladmitted": 9,
			"totaltransferred": 0,
			"totaldischarged": 12
		  },
		  {
			"dailyadmitted": 3,
			"dailytransferred": 0,
			"dailydischarged": 1,
			"date": "03 May",
			"totaladmitted": 12,
			"totaltransferred": 0,
			"totaldischarged": 13
		  },
		  {
			"dailyadmitted": 5,
			"dailytransferred": 2,
			"dailydischarged": 6,
			"date": "04 May",
			"totaladmitted": 17,
			"totaltransferred": 2,
			"totaldischarged": 19
		  },
		  {
			"dailyadmitted": 3,
			"dailytransferred": 1,
			"dailydischarged": 2,
			"date": "05 May",
			"totaladmitted": 20,
			"totaltransferred": 3,
			"totaldischarged": 29
		  },
		  {
			"dailyadmitted": 3,
			"dailytransferred": 0,
			"dailydischarged": 2,
			"date": "06 May",
			"totaladmitted": 23,
			"totaltransferred": 3,
			"totaldischarged": 31
		  },
		  {
			"dailyadmitted": 5,
			"dailytransferred": 2,
			"dailydischarged": 2,
			"date": "07 May",
			"totaladmitted": 28,
			"totaltransferred": 5,
			"totaldischarged": 33
		  },
		  {
			"dailyadmitted": 7,
			"dailytransferred": 3,
			"dailydischarged": 9,
			"date": "08 May",
			"totaladmitted": 35,
			"totaltransferred": 8,
			"totaldischarged": 42
		  },
		  {
			"dailyadmitted": 6,
			"dailytransferred": 0,
			"dailydischarged": 8,
			"date": "09 May",
			"totaladmitted": 41,
			"totaltransferred": 8,
			"totaldischarged": 50
		  },
		  {
			"dailyadmitted": 5,
			"dailytransferred": 0,
			"dailydischarged": 5,
			"date": "10 May",
			"totaladmitted": 46,
			"totaltransferred": 8,
			"totaldischarged": 60
		  },
		  {
			"dailyadmitted": 8,
			"dailytransferred": 0,
			"dailydischarged": 6,
			"date": "11 May",
			"totaladmitted": 54,
			"totaltransferred": 8,
			"totaldischarged": 66
		  },
		  {
			"dailyadmitted": 10,
			"dailytransferred": 0,
			"dailydischarged": 5,
			"date": "12 May",
			"totaladmitted": 64,
			"totaltransferred": 8,
			"totaldischarged": 71
		  },
		  {
			"dailyadmitted": 1,
			"dailytransferred": 0,
			"dailydischarged": 6,
			"date": "13 May",
			"totaladmitted": 65,
			"totaltransferred": 8,
			"totaldischarged": 77
		  },
		  {
			"dailyadmitted": 2,
			"dailytransferred": 3,
			"dailydischarged": 10,
			"date": "14 May",
			"totaladmitted": 67,
			"totaltransferred": 11,
			"totaldischarged": 87
		  },
		  {
			"dailyadmitted": 2,
			"dailytransferred": 0,
			"dailydischarged": 3,
			"date": "15 May",
			"totaladmitted": 69,
			"totaltransferred": 11,
			"totaldischarged": 90
		  },
		  {
			"dailyadmitted": 4,
			"dailytransferred": 1,
			"dailydischarged": 6,
			"date": "16 May",
			"totaladmitted": 73,
			"totaltransferred": 12,
			"totaldischarged": 96
		  },
		  {
			"dailyadmitted": 9,
			"dailytransferred": 0,
			"dailydischarged": 4,
			"date": "17 May",
			"totaladmitted": 82,
			"totaltransferred": 12,
			"totaldischarged": 100
		  },
		  {
			"dailyadmitted": 6,
			"dailytransferred": 0,
			"dailydischarged": 9,
			"date": "18 May",
			"totaladmitted": 88,
			"totaltransferred": 12,
			"totaldischarged": 109
		  },
		  {
			"dailyadmitted": 10,
			"dailytransferred": 0,
			"dailydischarged": 1,
			"date": "19 May",
			"totaladmitted": 98,
			"totaltransferred": 12,
			"totaldischarged": 110
		  },
		  {
			"dailyadmitted": 3,
			"dailytransferred": 0,
			"dailydischarged": 1,
			"date": "20 May",
			"totaladmitted": 101,
			"totaltransferred": 12,
			"totaldischarged": 111
		  },
		  {
			"dailyadmitted": 8,
			"dailytransferred": 1,
			"dailydischarged": 5,
			"date": "21 May",
			"totaladmitted": 109,
			"totaltransferred": 13,
			"totaldischarged": 116
		  },
		  {
			"dailyadmitted": 7,
			"dailytransferred": 2,
			"dailydischarged": 2,
			"date": "22 May",
			"totaladmitted": 116,
			"totaltransferred": 15,
			"totaldischarged": 118
		  },
		  {
			"dailyadmitted": 10,
			"dailytransferred": 0,
			"dailydischarged": 6,
			"date": "23 May",
			"totaladmitted": 126,
			"totaltransferred": 15,
			"totaldischarged": 124
		  },
		  {
			"dailyadmitted": 7,
			"dailytransferred": 0,
			"dailydischarged": 5,
			"date": "24 May",
			"totaladmitted": 133,
			"totaltransferred": 15,
			"totaldischarged": 129
		  },
		  {
			"dailyadmitted": 5,
			"dailytransferred": 0,
			"dailydischarged": 6,
			"date": "25 May",
			"totaladmitted": 138,
			"totaltransferred": 15,
			"totaldischarged": 135
		  },
		  {
			"dailyadmitted": 3,
			"dailytransferred": 1,
			"dailydischarged": 8,
			"date": "26 May",
			"totaladmitted": 141,
			"totaltransferred": 16,
			"totaldischarged": 143
		  },
		  {
			"dailyadmitted": 9,
			"dailytransferred": 1,
			"dailydischarged": 7,
			"date": "27 May",
			"totaladmitted": 150,
			"totaltransferred": 17,
			"totaldischarged": 150
		  },
		  {
			"dailyadmitted": 7,
			"dailytransferred": 2,
			"dailydischarged": 5,
			"date": "28 May",
			"totaladmitted": 157,
			"totaltransferred": 19,
			"totaldischarged": 159
		  },
		  {
			"dailyadmitted": 2,
			"dailytransferred": 0,
			"dailydischarged": 3,
			"date": "29 May",
			"totaladmitted": 159,
			"totaltransferred": 19,
			"totaldischarged": 162
		  },
		  {
			"dailyadmitted": 7,
			"dailytransferred": 1,
			"dailydischarged": 1,
			"date": "30 May",
			"totaladmitted": 166,
			"totaltransferred": 20,
			"totaldischarged": 163
		  },
		  {
			"dailyadmitted": 7,
			"dailytransferred": 1,
			"dailydischarged": 6,
			"date": "31 May",
			"totaladmitted": 173,
			"totaltransferred": 21,
			"totaldischarged": 169
		  },
		  {
			"dailyadmitted": 3,
			"dailytransferred": 0,
			"dailydischarged": 6,
			"date": "01 Jun",
			"totaladmitted": 176,
			"totaltransferred": 21,
			"totaldischarged": 175
		  },
		  {
			"dailyadmitted": 4,
			"dailytransferred": 0,
			"dailydischarged": 8,
			"date": "02 Jun",
			"totaladmitted": 180,
			"totaltransferred": 21,
			"totaldischarged": 183
		  },
		  {
			"dailyadmitted": 1,
			"dailytransferred": 0,
			"dailydischarged": 5,
			"date": "03 Jun",
			"totaladmitted": 181,
			"totaltransferred": 21,
			"totaldischarged": 188
		  },
		  {
			"dailyadmitted": 1,
			"dailytransferred": 2,
			"dailydischarged": 2,
			"date": "04 Jun",
			"totaladmitted": 182,
			"totaltransferred": 23,
			"totaldischarged": 190
		  },
		  {
			"dailyadmitted": 4,
			"dailytransferred": 1,
			"dailydischarged": 10,
			"date": "05 Jun",
			"totaladmitted": 186,
			"totaltransferred": 24,
			"totaldischarged": 200
		  },
		  {
			"dailyadmitted": 2,
			"dailytransferred": 0,
			"dailydischarged": 7,
			"date": "06 Jun",
			"totaladmitted": 188,
			"totaltransferred": 24,
			"totaldischarged": 207
		  },
		  {
			"dailyadmitted": 10,
			"dailytransferred": 2,
			"dailydischarged": 7,
			"date": "07 Jun",
			"totaladmitted": 198,
			"totaltransferred": 26,
			"totaldischarged": 214
		  },
		  {
			"dailyadmitted": 5,
			"dailytransferred": 3,
			"dailydischarged": 9,
			"date": "08 Jun",
			"totaladmitted": 203,
			"totaltransferred": 29,
			"totaldischarged": 223
		  },
		  {
			"dailyadmitted": 3,
			"dailytransferred": 0,
			"dailydischarged": 6,
			"date": "09 Jun",
			"totaladmitted": 206,
			"totaltransferred": 29,
			"totaldischarged": 229
		  },
		  {
			"dailyadmitted": 4,
			"dailytransferred": 0,
			"dailydischarged": 8,
			"date": "10 Jun",
			"totaladmitted": 210,
			"totaltransferred": 29,
			"totaldischarged": 237
		  },
		  {
			"dailyadmitted": 1,
			"dailytransferred": 0,
			"dailydischarged": 7,
			"date": "11 Jun",
			"totaladmitted": 211,
			"totaltransferred": 29,
			"totaldischarged": 244
		  },
		  {
			"dailyadmitted": 6,
			"dailytransferred": 0,
			"dailydischarged": 4,
			"date": "12 Jun",
			"totaladmitted": 217,
			"totaltransferred": 29,
			"totaldischarged": 248
		  },
		  {
			"dailyadmitted": 3,
			"dailytransferred": 0,
			"dailydischarged": 4,
			"date": "13 Jun",
			"totaladmitted": 220,
			"totaltransferred": 29,
			"totaldischarged": 252
		  },
		  {
			"dailyadmitted": 8,
			"dailytransferred": 3,
			"dailydischarged": 2,
			"date": "14 Jun",
			"totaladmitted": 228,
			"totaltransferred": 32,
			"totaldischarged": 254
		  },
		  {
			"dailyadmitted": 6,
			"dailytransferred": 0,
			"dailydischarged": 2,
			"date": "15 Jun",
			"totaladmitted": 234,
			"totaltransferred": 32,
			"totaldischarged": 256
		  },
		  {
			"dailyadmitted": 8,
			"dailytransferred": 1,
			"dailydischarged": 5,
			"date": "16 Jun",
			"totaladmitted": 242,
			"totaltransferred": 33,
			"totaldischarged": 261
		  },
		  {
			"dailyadmitted": 4,
			"dailytransferred": 0,
			"dailydischarged": 3,
			"date": "17 Jun",
			"totaladmitted": 246,
			"totaltransferred": 33,
			"totaldischarged": 264
		  },
		  {
			"dailyadmitted": 10,
			"dailytransferred": 0,
			"dailydischarged": 2,
			"date": "18 Jun",
			"totaladmitted": 256,
			"totaltransferred": 33,
			"totaldischarged": 266
		  },
		  {
			"dailyadmitted": 5,
			"dailytransferred": 0,
			"dailydischarged": 10,
			"date": "19 Jun",
			"totaladmitted": 261,
			"totaltransferred": 33,
			"totaldischarged": 276
		  },
		  {
			"dailyadmitted": 2,
			"dailytransferred": 0,
			"dailydischarged": 1,
			"date": "20 Jun",
			"totaladmitted": 263,
			"totaltransferred": 33,
			"totaldischarged": 277
		  },
		  {
			"dailyadmitted": 2,
			"dailytransferred": 1,
			"dailydischarged": 6,
			"date": "21 Jun",
			"totaladmitted": 265,
			"totaltransferred": 34,
			"totaldischarged": 283
		  },
		  {
			"dailyadmitted": 8,
			"dailytransferred": 2,
			"dailydischarged": 1,
			"date": "22 Jun",
			"totaladmitted": 273,
			"totaltransferred": 36,
			"totaldischarged": 284
		  },
		  {
			"dailyadmitted": 1,
			"dailytransferred": 0,
			"dailydischarged": 5,
			"date": "23 Jun",
			"totaladmitted": 274,
			"totaltransferred": 36,
			"totaldischarged": 289
		  },
		  {
			"dailyadmitted": 6,
			"dailytransferred": 0,
			"dailydischarged": 6,
			"date": "24 Jun",
			"totaladmitted": 280,
			"totaltransferred": 36,
			"totaldischarged": 295
		  },
		  {
			"dailyadmitted": 7,
			"dailytransferred": 0,
			"dailydischarged": 6,
			"date": "25 Jun",
			"totaladmitted": 287,
			"totaltransferred": 36,
			"totaldischarged": 301
		  },
		  {
			"dailyadmitted": 3,
			"dailytransferred": 1,
			"dailydischarged": 4,
			"date": "26 Jun",
			"totaladmitted": 290,
			"totaltransferred": 37,
			"totaldischarged": 305
		  },
		  {
			"dailyadmitted": 9,
			"dailytransferred": 1,
			"dailydischarged": 2,
			"date": "27 Jun",
			"totaladmitted": 299,
			"totaltransferred": 38,
			"totaldischarged": 307
		  },
		  {
			"dailyadmitted": 3,
			"dailytransferred": 2,
			"dailydischarged": 5,
			"date": "28 Jun",
			"totaladmitted": 302,
			"totaltransferred": 40,
			"totaldischarged": 312
		  },
		  {
			"dailyadmitted": 4,
			"dailytransferred": 0,
			"dailydischarged": 1,
			"date": "29 Jun",
			"totaladmitted": 306,
			"totaltransferred": 40,
			"totaldischarged": 313
		  },
		  {
			"dailyadmitted": 5,
			"dailytransferred": 1,
			"dailydischarged": 3,
			"date": "30 Jun",
			"totaladmitted": 311,
			"totaltransferred": 41,
			"totaldischarged": 316
		  }
	],
	
	"tested": [
		{
			"source": "MoH Press conference with Dr. Raman G",
			"testsconductedbyprivatelabs": "1334",
			"totalindividualstested": "",
			"totalpositivecases": "",
			"totalsamplestested": "38442",
			"updatetimestamp": "30/3/2020"
		}
	]
}